{
  "projects": [
    {
      "name": "Giới thiệu bản thân",
      "desc": "Tên tôi là Trần Hải Dương",
      "email": "",
      "sdt": "",
      "link": "https://github.com/duongthph21290",
      "author": "Hiện tại tôi đang là sinh viên kì 5 của trường FPT Polytechnic, chuyên ngành thiết kế Webiste",
      "id": 1
    },
    {
      "name": "Giới thiệu bản thân",
      "desc": "Facebook: Hai Duong",
      "email": "haiduong12122003@gmail.com",
      "sdt": "0969085244",
      "link": "https://github.com/duongthph21290",
      "author": "Địa chỉ:  Nam Từ Liêm - Hà Nội",
      "id": 2
    }
  ]
}